[
  {
    "RoomNumber": 2421,
    "SurgeMultiplier": 2,
    "Capacity": 3,
    "SquareFootage": 150,
    "Floor": 1,
    "BuildingId": 1
  },
  {
    "RoomNumber": 2422,
    "SurgeMultiplier": 2,
    "Capacity": 3,
    "SquareFootage": 150,
    "Floor": 1,
    "BuildingId": 1
  },
  {
    "RoomNumber": 2423,
    "SurgeMultiplier": 2,
    "Capacity": 3,
    "SquareFootage": 150,
    "Floor": 1,
    "BuildingId": 1
  },
  {
    "RoomNumber": 2424,
    "SurgeMultiplier": 2,
    "Capacity": 3,
    "SquareFootage": 150,
    "Floor": 1,
    "BuildingId": 1
  },
  {
    "RoomNumber": 2425,
    "SurgeMultiplier": 2,
    "Capacity": 3,
    "SquareFootage": 150,
    "Floor": 1,
    "BuildingId": 1
  },
  {
    "RoomNumber": 2426,
    "SurgeMultiplier": 2,
    "Capacity": 3,
    "SquareFootage": 150,
    "Floor": 1,
    "BuildingId": 1
  },
  {
    "RoomNumber": 2427,
    "SurgeMultiplier": 2,
    "Capacity": 3,
    "SquareFootage": 150,
    "Floor": 1,
    "BuildingId": 1
  },
  {
    "RoomNumber": 2428,
    "SurgeMultiplier": 2,
    "Capacity": 3,
    "SquareFootage": 150,
    "Floor": 1,
    "BuildingId": 1
  },
  {
    "RoomNumber": 2429,
    "SurgeMultiplier": 2,
    "Capacity": 3,
    "SquareFootage": 150,
    "Floor": 1,
    "BuildingId": 1
  },
  {
    "RoomNumber": 2430,
    "SurgeMultiplier": 2,
    "Capacity": 3,
    "SquareFootage": 150,
    "Floor": 1,
    "BuildingId": 1
  },
  {
    "RoomNumber": 2431,
    "SurgeMultiplier": 2,
    "Capacity": 3,
    "SquareFootage": 150,
    "Floor": 1,
    "BuildingId": 1
  },
  {
    "RoomNumber": 2432,
    "SurgeMultiplier": 2,
    "Capacity": 3,
    "SquareFootage": 150,
    "Floor": 1,
    "BuildingId": 1
  },
  {
    "RoomNumber": 2433,
    "SurgeMultiplier": 2,
    "Capacity": 3,
    "SquareFootage": 150,
    "Floor": 1,
    "BuildingId": 1
  },
  {
    "RoomNumber": 2434,
    "SurgeMultiplier": 2,
    "Capacity": 3,
    "SquareFootage": 150,
    "Floor": 1,
    "BuildingId": 1
  },
  {
    "RoomNumber": 2435,
    "SurgeMultiplier": 2,
    "Capacity": 3,
    "SquareFootage": 150,
    "Floor": 1,
    "BuildingId": 1
  },
  {
    "RoomNumber": 2436,
    "SurgeMultiplier": 2,
    "Capacity": 3,
    "SquareFootage": 150,
    "Floor": 1,
    "BuildingId": 1
  },
  {
    "RoomNumber": 2437,
    "SurgeMultiplier": 2,
    "Capacity": 3,
    "SquareFootage": 150,
    "Floor": 1,
    "BuildingId": 1
  },
  {
    "RoomNumber": 2438,
    "SurgeMultiplier": 2,
    "Capacity": 3,
    "SquareFootage": 150,
    "Floor": 1,
    "BuildingId": 1
  },
  {
    "RoomNumber": 2439,
    "SurgeMultiplier": 2,
    "Capacity": 3,
    "SquareFootage": 150,
    "Floor": 2,
    "BuildingId": 1
  },
  {
    "RoomNumber": 2440,
    "SurgeMultiplier": 2,
    "Capacity": 3,
    "SquareFootage": 150,
    "Floor": 2,
    "BuildingId": 1
  },
  {
    "RoomNumber": 2441,
    "SurgeMultiplier": 2,
    "Capacity": 3,
    "SquareFootage": 150,
    "Floor": 2,
    "BuildingId": 1
  },
  {
    "RoomNumber": 2442,
    "SurgeMultiplier": 2,
    "Capacity": 3,
    "SquareFootage": 150,
    "Floor": 2,
    "BuildingId": 1
  },
  {
    "RoomNumber": 2443,
    "SurgeMultiplier": 2,
    "Capacity": 3,
    "SquareFootage": 150,
    "Floor": 2,
    "BuildingId": 1
  },
  {
    "RoomNumber": 2444,
    "SurgeMultiplier": 2,
    "Capacity": 3,
    "SquareFootage": 150,
    "Floor": 2,
    "BuildingId": 1
  },
  {
    "RoomNumber": 2445,
    "SurgeMultiplier": 2,
    "Capacity": 3,
    "SquareFootage": 150,
    "Floor": 2,
    "BuildingId": 1
  },
  {
    "RoomNumber": 2446,
    "SurgeMultiplier": 2,
    "Capacity": 3,
    "SquareFootage": 150,
    "Floor": 2,
    "BuildingId": 1
  },
  {
    "RoomNumber": 2447,
    "SurgeMultiplier": 2,
    "Capacity": 3,
    "SquareFootage": 150,
    "Floor": 2,
    "BuildingId": 1
  },
  {
    "RoomNumber": 2448,
    "SurgeMultiplier": 2,
    "Capacity": 3,
    "SquareFootage": 150,
    "Floor": 2,
    "BuildingId": 1
  },
  {
    "RoomNumber": 2449,
    "SurgeMultiplier": 2,
    "Capacity": 3,
    "SquareFootage": 150,
    "Floor": 2,
    "BuildingId": 1
  },
  {
    "RoomNumber": 2450,
    "SurgeMultiplier": 2,
    "Capacity": 3,
    "SquareFootage": 150,
    "Floor": 2,
    "BuildingId": 1
  },
  {
    "RoomNumber": 2451,
    "SurgeMultiplier": 2,
    "Capacity": 3,
    "SquareFootage": 150,
    "Floor": 2,
    "BuildingId": 1
  },
  {
    "RoomNumber": 2452,
    "SurgeMultiplier": 2,
    "Capacity": 3,
    "SquareFootage": 150,
    "Floor": 2,
    "BuildingId": 1
  },
  {
    "RoomNumber": 2453,
    "SurgeMultiplier": 2,
    "Capacity": 3,
    "SquareFootage": 150,
    "Floor": 2,
    "BuildingId": 1
  },
  {
    "RoomNumber": 2454,
    "SurgeMultiplier": 2,
    "Capacity": 3,
    "SquareFootage": 150,
    "Floor": 2,
    "BuildingId": 1
  },
  {
    "RoomNumber": 2455,
    "SurgeMultiplier": 2,
    "Capacity": 3,
    "SquareFootage": 150,
    "Floor": 2,
    "BuildingId": 1
  },
  {
    "RoomNumber": 2456,
    "SurgeMultiplier": 2,
    "Capacity": 3,
    "SquareFootage": 150,
    "Floor": 2,
    "BuildingId": 1
  },
  {
    "RoomNumber": 2457,
    "SurgeMultiplier": 2,
    "Capacity": 3,
    "SquareFootage": 150,
    "Floor": 2,
    "BuildingId": 1
  },
  {
    "RoomNumber": 2458,
    "SurgeMultiplier": 2,
    "Capacity": 3,
    "SquareFootage": 150,
    "Floor": 2,
    "BuildingId": 1
  },
  {
    "RoomNumber": 3330,
    "SurgeMultiplier": 2,
    "Capacity": 3,
    "SquareFootage": 150,
    "Floor": 1,
    "BuildingId": 2
  },
  {
    "RoomNumber": 3331,
    "SurgeMultiplier": 2,
    "Capacity": 3,
    "SquareFootage": 150,
    "Floor": 1,
    "BuildingId": 2
  },
  {
    "RoomNumber": 3332,
    "SurgeMultiplier": 2,
    "Capacity": 3,
    "SquareFootage": 150,
    "Floor": 1,
    "BuildingId": 2
  },
  {
    "RoomNumber": 3333,
    "SurgeMultiplier": 2,
    "Capacity": 3,
    "SquareFootage": 150,
    "Floor": 1,
    "BuildingId": 2
  },
  {
    "RoomNumber": 3334,
    "SurgeMultiplier": 2,
    "Capacity": 3,
    "SquareFootage": 150,
    "Floor": 1,
    "BuildingId": 2
  },
  {
    "RoomNumber": 3335,
    "SurgeMultiplier": 2,
    "Capacity": 3,
    "SquareFootage": 150,
    "Floor": 1,
    "BuildingId": 2
  },
  {
    "RoomNumber": 3336,
    "SurgeMultiplier": 2,
    "Capacity": 3,
    "SquareFootage": 150,
    "Floor": 1,
    "BuildingId": 2
  },
  {
    "RoomNumber": 3337,
    "SurgeMultiplier": 2,
    "Capacity": 3,
    "SquareFootage": 150,
    "Floor": 1,
    "BuildingId": 2
  },
  {
    "RoomNumber": 3338,
    "SurgeMultiplier": 2,
    "Capacity": 3,
    "SquareFootage": 150,
    "Floor": 1,
    "BuildingId": 2
  },
  {
    "RoomNumber": 3339,
    "SurgeMultiplier": 2,
    "Capacity": 3,
    "SquareFootage": 150,
    "Floor": 1,
    "BuildingId": 2
  },
  {
    "RoomNumber": 3340,
    "SurgeMultiplier": 2,
    "Capacity": 3,
    "SquareFootage": 150,
    "Floor": 1,
    "BuildingId": 2
  },
  {
    "RoomNumber": 3341,
    "SurgeMultiplier": 2,
    "Capacity": 3,
    "SquareFootage": 150,
    "Floor": 1,
    "BuildingId": 2
  },
  {
    "RoomNumber": 3342,
    "SurgeMultiplier": 2,
    "Capacity": 3,
    "SquareFootage": 150,
    "Floor": 1,
    "BuildingId": 2
  },
  {
    "RoomNumber": 3343,
    "SurgeMultiplier": 2,
    "Capacity": 3,
    "SquareFootage": 150,
    "Floor": 1,
    "BuildingId": 2
  },
  {
    "RoomNumber": 3344,
    "SurgeMultiplier": 2,
    "Capacity": 3,
    "SquareFootage": 150,
    "Floor": 1,
    "BuildingId": 2
  },
  {
    "RoomNumber": 3345,
    "SurgeMultiplier": 2,
    "Capacity": 3,
    "SquareFootage": 150,
    "Floor": 1,
    "BuildingId": 2
  },
  {
    "RoomNumber": 3346,
    "SurgeMultiplier": 2,
    "Capacity": 3,
    "SquareFootage": 150,
    "Floor": 2,
    "BuildingId": 2
  },
  {
    "RoomNumber": 3347,
    "SurgeMultiplier": 2,
    "Capacity": 3,
    "SquareFootage": 150,
    "Floor": 2,
    "BuildingId": 2
  },
  {
    "RoomNumber": 3348,
    "SurgeMultiplier": 2,
    "Capacity": 3,
    "SquareFootage": 150,
    "Floor": 2,
    "BuildingId": 2
  },
  {
    "RoomNumber": 3349,
    "SurgeMultiplier": 2,
    "Capacity": 3,
    "SquareFootage": 150,
    "Floor": 2,
    "BuildingId": 2
  },
  {
    "RoomNumber": 3350,
    "SurgeMultiplier": 2,
    "Capacity": 3,
    "SquareFootage": 150,
    "Floor": 2,
    "BuildingId": 2
  },
  {
    "RoomNumber": 3351,
    "SurgeMultiplier": 2,
    "Capacity": 3,
    "SquareFootage": 150,
    "Floor": 2,
    "BuildingId": 2
  },
  {
    "RoomNumber": 3352,
    "SurgeMultiplier": 2,
    "Capacity": 3,
    "SquareFootage": 150,
    "Floor": 2,
    "BuildingId": 2
  },
  {
    "RoomNumber": 3353,
    "SurgeMultiplier": 2,
    "Capacity": 3,
    "SquareFootage": 150,
    "Floor": 2,
    "BuildingId": 2
  },
  {
    "RoomNumber": 3354,
    "SurgeMultiplier": 2,
    "Capacity": 3,
    "SquareFootage": 150,
    "Floor": 2,
    "BuildingId": 2
  },
  {
    "RoomNumber": 3355,
    "SurgeMultiplier": 2,
    "Capacity": 3,
    "SquareFootage": 150,
    "Floor": 2,
    "BuildingId": 2
  },
  {
    "RoomNumber": 3356,
    "SurgeMultiplier": 2,
    "Capacity": 3,
    "SquareFootage": 150,
    "Floor": 2,
    "BuildingId": 2
  },
  {
    "RoomNumber": 3357,
    "SurgeMultiplier": 2,
    "Capacity": 3,
    "SquareFootage": 150,
    "Floor": 2,
    "BuildingId": 2
  },
  {
    "RoomNumber": 3358,
    "SurgeMultiplier": 2,
    "Capacity": 3,
    "SquareFootage": 150,
    "Floor": 2,
    "BuildingId": 2
  },
  {
    "RoomNumber": 3359,
    "SurgeMultiplier": 2,
    "Capacity": 3,
    "SquareFootage": 150,
    "Floor": 2,
    "BuildingId": 2
  },
  {
    "RoomNumber": 3360,
    "SurgeMultiplier": 2,
    "Capacity": 3,
    "SquareFootage": 150,
    "Floor": 2,
    "BuildingId": 2
  },
  {
    "RoomNumber": 3361,
    "SurgeMultiplier": 2,
    "Capacity": 3,
    "SquareFootage": 150,
    "Floor": 2,
    "BuildingId": 2
  }
]
